
{"data":
[{"id":"001","no01":"sb23651420","name":"危险品仓库","type":"防腐蚀仓库","num":"100吨","time":"2012-02-13","per":"刘勇","unit":"德阳仓库管理公司","tele":"13612365321","addr":"德阳市大人村","note":"腐蚀类，防泄漏","oper":"1"},
  {"id":"002","no01":"sb02315623","name":"危险品仓库","type":"防毒仓库","num":"150吨","time":"2013-02-10","per":"张江华","unit":"青白江大明仓库管理公司","tele":"13623659621","addr":"清白江大合村21号","note":"腐蚀类","oper":"1"},
  {"id":"003","no01":"sb03698521","name":"防爆仓库","type":"防爆仓库","num":"100吨","time":"2013-05-07","per":"李闪伍","unit":"绵阳肖明仓库管理公司","tele":"15023984529","addr":"绵阳市大兴路112号","note":"腐蚀类","oper":"1"},
  {"id":"004","no01":"sb69325841","name":"防爆仓库","type":"防爆仓库","num":"50吨","time":"2014-06-11","per":"吴舆传","unit":"成华仓库管理公司","tele":"13698521475","addr":"成都市成华区120号","note":"腐蚀类","oper":"1"},
  {"id":"005","no01":"sb85723692","name":"专用仓库","type":"防腐蚀仓库","num":"50吨","time":"2015-09-13","per":"刘海","unit":"资阳刘海仓管管理公司","tele":"13769886236","addr":"资阳市大雁路10号","note":"腐蚀类","oper":"1"},
  {"id":"006","no01":"sb36521203","name":"专用仓库","type":"防腐蚀仓库","num":"150吨","time":"2015-12-03","per":"张一白","unit":"红光仓库管理公司","tele":"13897562158","addr":"红光镇120号","note":"腐蚀类","oper":"1"},
  {"id":"007","no01":"sb89652301","name":"普通仓库","type":"普通仓库","num":"500吨","time":"2016-08-20","per":"肖红明","unit":"绵阳万一仓库管理公司","tele":"13945756238","addr":"绵阳市大肖村231号","note":"腐蚀类","oper":"1"},
  {"id":"008","no01":"sb85623012","name":"冷冻仓库","type":"冷冻仓库","num":"200吨","time":"2015-02-09","per":"万华林","unit":"平安仓库管理公司","tele":"13956243600","addr":"新都区大华路23号","note":"腐蚀类","oper":"1"},
  {"id":"009","no01":"sb52136201","name":"专用仓库","type":"防腐蚀仓库","num":"1000吨","time":"2017-02-13","per":"李阳明","unit":"大顺仓库管理公司","tele":"135869234562","addr":"德阳市小林路23号","note":"腐蚀类","oper":"1"},
  {"id":"010","no01":"sb23654120","name":"专用仓库","type":"毒气仓库","num":"500吨","time":"2015-02-18","per":"刘丰运","unit":"大华仓库管理公司","tele":"15012369874","addr":"成都市新都区23号","note":"腐蚀，防爆类","oper":"1"}









]}